params.v
`define INSTR_SIZE 31
`define ADDR_SIZE 31

decode.v
`ifdef __ICARUS__
    `ifndef INCLUDE_PARAMS
        `include "params.v"
    `endif
`endif

module decode(
    input wire clk,
    input wire reset,

    //Interface pipeline in
    input wire [`ADDR_SIZE : 0] PC_in,
    input wire [`INSTR_SIZE : 0] instr_in,
    input wire pipeline_in_valid,

    //Interface pipeline out
    output reg [`ADDR_SIZE : 0] PC_out,
    output reg [`INSTR_SIZE : 0] instr_out,
    output reg pipeline_out_valid,

    input wire stall,
    input wire flush
);

    reg rg_stall, rg_flush;

    always@(posedge(stall)) rg_stall <= 1;
    always@(posedge(flush)) begin
        rg_flush <= 1;
        $display("%0d\tDECODE: Flush", $time);
    end

    always @(posedge(clk)) begin
        if(reset || rg_flush) begin
            pipeline_out_valid <= 0;
        end
        else if(rg_stall) begin
            PC_out <= PC_out;
            instr_out <= instr_out;
            pipeline_out_valid <= pipeline_out_valid;
        end
        else if(pipeline_in_valid) begin
            PC_out <= PC_in;
            instr_out <= instr_in;
            pipeline_out_valid <= pipeline_in_valid;
        end
        rg_stall <= 0;
        rg_flush <= 0;
    end

`ifdef SIMULATE
    always@(posedge(clk)) begin
        if(pipeline_out_valid)
            $display("%0d\tDECODE: reset: %b PC: %h instr: %h", $time, reset, PC_out, instr_out);
    end
`endif


endmodule // decode

fetch.v
`ifdef __ICARUS__
    `ifndef INCLUDE_PARAMS
        `include "params.v"
    `endif
`endif

module fetch(
    input wire clk,
    input wire reset,

    //Interface with memory
    output reg [ `ADDR_SIZE : 0] mem_rd_addr,
    output reg mem_rd_enable,
    input wire [`INSTR_SIZE : 0] mem_rd_data,
    input wire mem_rd_ready,

    //Interface with pipeline
    output reg [`INSTR_SIZE : 0] instr,
    output reg [ `ADDR_SIZE : 0] PC,
    output reg pipeline_valid,

    input wire flush,
    input wire [`INSTR_SIZE : 0] flush_addr,

    input wire stall
);

    reg [`ADDR_SIZE : 0] next_PC;
    reg [`INSTR_SIZE : 0] rg_data_from_mem;
    reg mem_valid;
    reg rg_flush;
    reg rg_stall;

    always@(posedge(flush)) begin
        rg_flush <= 1;
        $display("%0d\tFETCH: Flush - Addr: %h", $time, flush_addr);
    end
    always@(posedge(stall)) rg_stall <= 1;

    always@(mem_rd_enable or mem_rd_ready or reset or next_PC or rg_flush) begin
        if(reset || rg_flush) begin
            mem_valid <= 0;
        end
        else if(!mem_rd_enable) begin
            mem_rd_addr <= next_PC;
            mem_rd_enable <= 1;
        end
        else if(mem_rd_enable && mem_rd_ready) begin
            rg_data_from_mem <= mem_rd_data;
            mem_valid <= 1;
        end
    end

    always@(posedge(clk)) begin
        if(reset) begin
            PC <= 0;
            next_PC <= 0;
            pipeline_valid <= 0;
            mem_rd_enable <= 0;
        end
        else if(rg_flush) begin
            PC <= PC;
            next_PC <= flush_addr;
            pipeline_valid <= 0;
            mem_rd_enable <= 0;
        end
        else if(mem_valid) begin
            instr <= rg_data_from_mem;
            pipeline_valid <= 1;
            mem_rd_enable <= 0;
            if(rg_stall) begin
                PC <= PC;
                next_PC <= next_PC;
            end
            else begin
                PC <= next_PC;
                next_PC <= next_PC + 'd4;
            end
        end
        else begin
            pipeline_valid <= 0;
        end
        rg_flush <= 0;
        rg_stall <= 0;
    end

`ifdef SIMULATE
    always@(posedge(clk)) begin
        if(pipeline_valid)
            $display("%0d\tFETCH: reset: %b mem_rd_enable: %b mem_rd_ready: %b PC: %h nextPC: %h instr: %h", $time, reset, mem_rd_enable, mem_rd_ready, PC, next_PC, instr);
    end

`endif

endmodule

tb.v
`ifdef __ICARUS__
    `define SIMULATE
    `ifndef INCLUDE_PARAMS
        `include "params.v"
    `endif
    `include "fetch.v"
    `include "decode.v"
`endif

module tb;
    reg clk;
    reg reset;
    wire [`ADDR_SIZE : 0] PC_f_d;
    wire [`INSTR_SIZE : 0] instr_f_d;
    wire pipe_valid;
    wire en;
    reg stall, flush;
    reg [`INSTR_SIZE : 0] faddr;
    wire [`ADDR_SIZE : 0] addr;
    reg [`INSTR_SIZE : 0] data;
    reg strobe;
    fetch fetch
    (
        .reset(reset),
        .clk (clk),
        .PC(PC_f_d),
        .instr(instr_f_d),
        .pipeline_valid(pipe_valid),
        .mem_rd_enable(en),
        .mem_rd_addr(addr),
        .mem_rd_ready(strobe),
        .mem_rd_data(data),
        .stall(stall),
        .flush(flush),
        .flush_addr(faddr)
    );

    decode decode
    (
        .clk(clk),
        .reset(reset),
        .PC_in(PC_f_d),
        .instr_in(instr_f_d),
        .pipeline_in_valid(pipe_valid),
        .stall(stall),
        .flush(flush)
    );
    always #(5) clk=~clk;

    initial begin
        $dumpfile("wave.vcd");
        $dumpvars(0, tb);
    end

    initial begin
        reset=1;    clk=1; strobe=0; stall=0; flush =0; faddr = 0;
        #7 reset = 0;
        // repeat(1) begin
        //     #40 stall = 1;
        //     #2 stall = 0;
        // end
        #50 faddr = 'd4;
        flush = 1;
        #2 flush = 0;
        #50 $finish();
    end

    always@(posedge(en)) begin
        #5 data = addr + 'h8000; strobe = 1;
        #2 strobe = 0;
    end

    always@(posedge(clk)) $display("************************\n");

endmodule

wave.vcd
$date
	Tue Jan 02 16:31:41 2018
$end
$version
	Icarus Verilog
$end
$timescale
	1s
$end
$scope module tb $end
$var wire 1 ! pipe_valid $end
$var wire 32 " instr_f_d [31:0] $end
$var wire 1 # en $end
$var wire 32 $ addr [31:0] $end
$var wire 32 % PC_f_d [31:0] $end
$var reg 1 & clk $end
$var reg 32 ' data [31:0] $end
$var reg 32 ( faddr [31:0] $end
$var reg 1 ) flush $end
$var reg 1 * reset $end
$var reg 1 + stall $end
$var reg 1 , strobe $end
$scope module decode $end
$var wire 1 & clk $end
$var wire 1 ) flush $end
$var wire 1 * reset $end
$var wire 1 + stall $end
$var wire 1 ! pipeline_in_valid $end
$var wire 32 - instr_in [31:0] $end
$var wire 32 . PC_in [31:0] $end
$var reg 32 / PC_out [31:0] $end
$var reg 32 0 instr_out [31:0] $end
$var reg 1 1 pipeline_out_valid $end
$var reg 1 2 rg_flush $end
$var reg 1 3 rg_stall $end
$upscope $end
$scope module fetch $end
$var wire 1 & clk $end
$var wire 1 ) flush $end
$var wire 32 4 flush_addr [31:0] $end
$var wire 32 5 mem_rd_data [31:0] $end
$var wire 1 , mem_rd_ready $end
$var wire 1 * reset $end
$var wire 1 + stall $end
$var reg 32 6 PC [31:0] $end
$var reg 32 7 instr [31:0] $end
$var reg 32 8 mem_rd_addr [31:0] $end
$var reg 1 # mem_rd_enable $end
$var reg 1 9 mem_valid $end
$var reg 32 : next_PC [31:0] $end
$var reg 1 ! pipeline_valid $end
$var reg 32 ; rg_data_from_mem [31:0] $end
$var reg 1 < rg_flush $end
$var reg 1 = rg_stall $end
$upscope $end
$upscope $end
$enddefinitions $end
#0
$dumpvars
0=
0<
bx ;
b0 :
09
bx 8
bx 7
b0 6
bx 5
b0 4
03
02
01
bx 0
bx /
b0 .
bx -
0,
0+
1*
0)
b0 (
bx '
1&
b0 %
bx $
0#
bx "
0!
$end
#5
0&
#10
1#
b0 $
b0 8
1&
0*
#15
0&
#20
1&
#25
0&
#30
19
b1000000000000000 ;
1&
1,
b1000000000000000 '
b1000000000000000 5
#35
0&
0,
#40
b100 $
b100 8
b100 :
1#
1!
b1000000000000000 "
b1000000000000000 -
b1000000000000000 7
1&
#45
0&
#50
b1000 $
b1000 8
11
b1000000000000000 0
b0 /
b1000 :
b100 %
b100 .
b100 6
1#
1&
#55
0&
#60
b100 $
b100 8
1#
0!
b100 :
b100 /
b1000000000001000 ;
0<
02
1&
1,
b1000000000001000 '
b1000000000001000 5
1)
b100 (
b100 4
#65
0&
0,
0)
#70
b1000 $
b1000 8
b1000 :
1#
1!
b1000000000001000 "
b1000000000001000 -
b1000000000001000 7
1&
#75
0&
#80
b1100 $
b1100 8
b1100 :
b1000 %
b1000 .
b1000 6
1#
b1000000000001000 0
1&
#85
0&
#90
b10000 $
b10000 8
b1000 /
b10000 :
b1100 %
b1100 .
b1100 6
1#
b1000000000001100 ;
1&
1,
b1000000000001100 '
b1000000000001100 5
#95
0&
0,
#100
b10100 $
b10100 8
b10100 :
b10000 %
b10000 .
b10000 6
1#
b1000000000001100 "
b1000000000001100 -
b1000000000001100 7
b1100 /
1&
#105
0&
#110
b11000 $
b11000 8
b1000000000001100 0
b10000 /
b11000 :
b10100 %
b10100 .
b10100 6
1#
1&
